TxColor.py
__init__.py
txcolorlib-1.0.3.dist-info/METADATA
txcolorlib-1.0.3.dist-info/WHEEL
txcolorlib-1.0.3.dist-info/licenses/LICENSE
txcolorlib-1.0.3.dist-info/RECORD
