Metadata-Version: 2.1
Name: TxColorLib
Version: 1.0.3
Summary: TxColor gives you the ability to format text with colors right in it! You can also provide a string and it will look like this: <r>red</r>.
Project-URL: Homepage, https://github.com/spytaspund/TxColor
Author-email: spytaspund <paren.sanek@mail.ru>
License: MIT License
Classifier: License :: OSI Approved :: MIT License
Classifier: Operating System :: OS Independent
Classifier: Programming Language :: Python :: 3
Requires-Python: >=3.7
